Workbook

Sheet Backlog
A1: ID | B1: Epic | C1: User story | D1: Acceptance criteria | E1: Component | F1: Priority | G1: Points | H1: Status | I1: Spec ref
A2: LZ-001 | B2: Foundation & Developer Experience | C2: As a developer, I want a one-command local stack so that I can run the whole system without manual setup | D2: docker compose up brings up Postgres, LocalStack and the API; API health returns UP | E2: Infra | F2: Must | G2: 5 | H2: Done | I2: Tech §5
A3: LZ-002 | B3: Foundation & Developer Experience | C3: As a developer, I want the database schema created automatically so that environments never drift | D3: Flyway applies V1 on startup; all 21 tables present; re-runs are no-ops | E3: Backend | F3: Must | G3: 8 | H3: Done | I3: Tech §2
A4: LZ-003 | B4: Foundation & Developer Experience | C4: As a developer, I want enum columns that map cleanly to JPA so that entities need no casting | D4: Native enums replaced by varchar + CHECK; defaults and partial index preserved | E4: Backend | F4: Must | G4: 3 | H4: Done | I4: Tech §2
A5: LZ-004 | B5: Foundation & Developer Experience | C5: As a client developer, I want one error shape across every endpoint so that I parse errors in one place | D5: All errors return code/message/fields/timestamp; codes are stable and documented | E5: Backend | F5: Must | G5: 3 | H5: Done | I5: —
A6: LZ-005 | B6: Foundation & Developer Experience | C6: As a client developer, I want a generated API client so that backend and app cannot drift | D6: OpenAPI served at /v3/api-docs; Dart client generated from it; regeneration documented | E6: Shared | F6: Must | G6: 5 | H6: Done | I6: —
A7: LZ-006 | B7: Foundation & Developer Experience | C7: As a developer, I want CI on every push so that regressions are caught before merge | D7: Backend and Flutter tests run on push; failures block the merge | E7: Infra | F7: Must | G7: 3 | H7: Not Started | I7: —
A8: LZ-007 | B8: Foundation & Developer Experience | C8: As a developer, I want seed data so that screens can be built against realistic records | D8: One landlord, one property with a bedspace and a whole unit, leases and billing periods | E8: Backend | F8: Should | G8: 3 | H8: Not Started | I8: —
A9: LZ-008 | B9: Foundation & Developer Experience | C9: As a developer, I want integration tests against real Postgres so that schema constraints are exercised | D9: Testcontainers suite runs in CI; partial indexes and CHECKs are covered | E9: Backend | F9: Must | G9: 5 | H9: In Progress | I9: —
A10: LZ-009 | B10: Foundation & Developer Experience | C10: As a developer, I want money and date conventions fixed so that rounding never drifts | D10: BigDecimal for peso amounts, LocalDate for due dates, UTC for instants; documented | E10: Backend | F10: Should | G10: 2 | H10: Not Started | I10: Tech §7
A11: LZ-010 | B11: Design System | C11: As a designer, I want the design language as code so that both apps look like one product | D11: Colour and type tokens match design language v2; shared package consumed by both apps | E11: Shared | F11: Must | G11: 5 | H11: Done | I11: Design v2
A12: LZ-011 | B12: Design System | C12: As a landlord, I want status shown consistently so that I can scan a long list quickly | D12: Dot+pill chip; teal=paid, amber=pending, red=overdue; mapping covered by tests | E12: Shared | F12: Must | G12: 2 | H12: Done | I12: Design v2
A13: LZ-012 | B13: Design System | C13: As a user, I want the app to feel distinctly Filipino so that it does not read as generic software | D13: Capiz-lattice header renders at low contrast behind content on both apps | E13: Shared | F13: Should | G13: 3 | H13: Done | I13: Design v2
... A81: LZ-145 | B81: Deployment & Operations | C81: As an operator, I want alerting on the API so that I hear about downtime before users do | D81: Uptime check on /actuator/health with a notification channel | E81: Infra | F81: Should | G81: 3 | H81: Not Started | I81: —

Sheet Epics
A1: Epic ID | B1: Epic | C1: Goal | D1: Stories | E1: Points | F1: Done | G1: Points done | H1: % complete
A2: E1 | B2: Foundation & Developer Experience | C2: The stack runs locally, the schema is versioned, and contracts are generated rather than hand-kept | D2: =COUNTIF(Backlog!$B$2:$B$81,$B2) | E2: =SUMIF(Backlog!$B$2:$B$81,$B2,Backlog!$G$2:$G$81) | F2: =COUNTIFS(Backlog!$B$2:$B$81,$B2,Backlog!$H$2:$H$81,"Done") | G2: =SUMIFS(Backlog!$G$2:$G$81,Backlog!$B$2:$B$81,$B2,Backlog!$H$2:$H$81,"Done") | H2: =IF($E2=0,0,$G2/$E2)
A3: E2 | B3: Design System | C3: One visual language, shared by both clients, matching design language v2 | D3: =COUNTIF(Backlog!$B$2:$B$81,$B3) | E3: =SUMIF(Backlog!$B$2:$B$81,$B3,Backlog!$G$2:$G$81) | F3: =COUNTIFS(Backlog!$B$2:$B$81,$B3,Backlog!$H$2:$H$81,"Done") | G3: =SUMIFS(Backlog!$G$2:$G$81,Backlog!$B$2:$B$81,$B3,Backlog!$H$2:$H$81,"Done") | H3: =IF($E3=0,0,$G3/$E3)
A4: E3 | B4: Accounts & Access | C4: Identity, sessions, and the authorisation rules that keep landlords and tenants apart | D4: =COUNTIF(Backlog!$B$2:$B$81,$B4) | E4: =SUMIF(Backlog!$B$2:$B$81,$B4,Backlog!$G$2:$G$81) | F4: =COUNTIFS(Backlog!$B$2:$B$81,$B4,Backlog!$H$2:$H$81,"Done") | G4: =SUMIFS(Backlog!$G$2:$G$81,Backlog!$B$2:$B$81,$B4,Backlog!$H$2:$H$81,"Done") | H4: =IF($E4=0,0,$G4/$E4)
A5: E4 | B5: Property, Unit & Bed | C5: The rentable inventory, including bedspaces as first-class things | D5: =COUNTIF(Backlog!$B$2:$B$81,$B5) | E5: =SUMIF(Backlog!$B$2:$B$81,$B5,Backlog!$G$2:$G$81) | F5: =COUNTIFS(Backlog!$B$2:$B$81,$B5,Backlog!$H$2:$H$81,"Done") | G5: =SUMIFS(Backlog!$G$2:$G$81,Backlog!$B$2:$B$81,$B5,Backlog!$H$2:$H$81,"Done") | H5: =IF($E5=0,0,$G5/$E5)
A6: E5 | B6: Leases | C6: Attaching a tenant to a unit or bed, with landlord-controlled due dates | D6: =COUNTIF(Backlog!$B$2:$B$81,$B6) | E6: =SUMIF(Backlog!$B$2:$B$81,$B6,Backlog!$G$2:$G$81) | F6: =COUNTIFS(Backlog!$B$2:$B$81,$B6,Backlog!$H$2:$H$81,"Done") | G6: =SUMIFS(Backlog!$G$2:$G$81,Backlog!$B$2:$B$81,$B6,Backlog!$H$2:$H$81,"Done") | H6: =IF($E6=0,0,$G6/$E6)
A7: E6 | B7: Billing & Payments | C7: Rent tracked per period and settled by proof-of-payment, with no gateway | D7: =COUNTIF(Backlog!$B$2:$B$81,$B7) | E7: =SUMIF(Backlog!$B$2:$B$81,$B7,Backlog!$G$2:$G$81) | F7: =COUNTIFS(Backlog!$B$2:$B$81,$B7,Backlog!$H$2:$H$81,"Done") | G7: =SUMIFS(Backlog!$G$2:$G$81,Backlog!$B$2:$B$81,$B7,Backlog!$H$2:$H$81,"Done") | H7: =IF($E7=0,0,$G7/$E7)
A8: E7 | B8: Maintenance | C8: Tenants report problems in plain words; landlords track them to done | D8: =COUNTIF(Backlog!$B$2:$B$81,$B8) | E8: =SUMIF(Backlog!$B$2:$B$81,$B8,Backlog!$G$2:$G$81) | F8: =COUNTIFS(Backlog!$B$2:$B$81,$B8,Backlog!$H$2:$H$81,"Done") | G8: =SUMIFS(Backlog!$G$2:$G$81,Backlog!$B$2:$B$81,$B8,Backlog!$H$2:$H$81,"Done") | H8: =IF($E8=0,0,$G8/$E8)
A9: E8 | B9: Staff | C9: Per-property caretakers with granular, revocable permissions | D9: =COUNTIF(Backlog!$B$2:$B$81,$B9) | E9: =SUMIF(Backlog!$B$2:$B$81,$B9,Backlog!$G$2:$G$81) | F9: =COUNTIFS(Backlog!$B$2:$B$81,$B9,Backlog!$H$2:$H$81,"Done") | G9: =SUMIFS(Backlog!$G$2:$G$81,Backlog!$B$2:$B$81,$B9,Backlog!$H$2:$H$81,"Done") | H9: =IF($E9=0,0,$G9/$E9)
A10: E9 | B10: Documents | C10: Contracts, IDs and receipts attached to the record they belong to | D10: =COUNTIF(Backlog!$B$2:$B$81,$B10) | E10: =SUMIF(Backlog!$B$2:$B$81,$B10,Backlog!$G$2:$G$81) | F10: =COUNTIFS(Backlog!$B$2:$B$81,$B10,Backlog!$H$2:$H$81,"Done") | G10: =SUMIFS(Backlog!$G$2:$G$81,Backlog!$B$2:$B$81,$B10,Backlog!$H$2:$H$81,"Done") | H10: =IF($E10=0,0,$G10/$E10)
A11: E10 | B11: Notices | C11: Announcements with dynamic audience, expiry and read receipts | D11: =COUNTIF(Backlog!$B$2:$B$81,$B11) | E11: =SUMIF(Backlog!$B$2:$B$81,$B11,Backlog!$G$2:$G$81) | F11: =COUNTIFS(Backlog!$B$2:$B$81,$B11,Backlog!$H$2:$H$81,"Done") | G11: =SUMIFS(Backlog!$G$2:$G$81,Backlog!$B$2:$B$81,$B11,Backlog!$H$2:$H$81,"Done") | H11: =IF($E11=0,0,$G11/$E11)
A12: E11 | B12: Notifications | C12: In-app signals for rent, payments, maintenance and notices | D12: =COUNTIF(Backlog!$B$2:$B$81,$B12) | E12: =SUMIF(Backlog!$B$2:$B$81,$B12,Backlog!$G$2:$G$81) | F12: =COUNTIFS(Backlog!$B$2:$B$81,$B12,Backlog!$H$2:$H$81,"Done") | G12: =SUMIFS(Backlog!$G$2:$G$81,Backlog!$B$2:$B$81,$B12,Backlog!$H$2:$H$81,"Done") | H12: =IF($E12=0,0,$G12/$E12)
A13: E12 | B13: Reporting | C13: Occupancy, income, overdue and maintenance views over live data | D13: =COUNTIF(Backlog!$B$2:$B$81,$B13) | E13: =SUMIF(Backlog!$B$2:$B$81,$B13,Backlog!$G$2:$G$81) | F13: =COUNTIFS(Backlog!$B$2:$B$81,$B13,Backlog!$H$2:$H$81,"Done") | G13: =SUMIFS(Backlog!$G$2:$G$81,Backlog!$B$2:$B$81,$B13,Backlog!$H$2:$H$81,"Done") | H13: =IF($E13=0,0,$G13/$E13)
... A16: E15 | B16: Deployment & Operations | C16: Reproducible infrastructure, automated releases and basic observability | D16: =COUNTIF(Backlog!$B$2:$B$81,$B16) | E16: =SUMIF(Backlog!$B$2:$B$81,$B16,Backlog!$G$2:$G$81) | F16: =COUNTIFS(Backlog!$B$2:$B$81,$B16,Backlog!$H$2:$H$81,"Done") | G16: =SUMIFS(Backlog!$G$2:$G$81,Backlog!$B$2:$B$81,$B16,Backlog!$H$2:$H$81,"Done") | H16: =IF($E16=0,0,$G16/$E16)
B17: Total | D17: =SUM(D2:D17) | E17: =SUM(E2:E17) | F17: =SUM(F2:F17) | G17: =SUM(G2:G17) | H17: =IF($E17=0,0,$G17/$E17)

Sheet Legend
A1: Field | B1: Value | C1: Meaning
A2: Status | B2: Done | C2: Built and verified against a running system
A3: Status | B3: In Progress | C3: Started; see the note in the commit history for what remains
A4: Status | B4: Not Started | C4: Not begun
A5: Status | B5: Blocked | C5: Cannot proceed until something else lands
A6: Priority | B6: Must | C6: MVP does not ship without it
A7: Priority | B7: Should | C7: Expected in MVP, but could slip a release
A8: Priority | B8: Could | C8: Valuable, not expected in MVP
A9: Points | B9: 1, 2, 3, 5, 8 | C9: Relative effort, Fibonacci. 8 signals a story worth splitting
A10: Component | B10: Backend | C10: Spring Boot API
A11: Component | B11: Mobile | C11: Flutter app for landlord, tenant and staff
A12: Component | B12: Admin Web | C12: Flutter web console for Lizmo staff
... A17: Spec ref | B17: Design v2 | C17: lizmo_design_language_v2.html, the canonical design language
A19: Note | B19: Statuses reflect the repository as of 14 Aug 2026. Stories are derived from Lizmo_Product_Spec_v1.md and Lizmo_Tech_Spec_v1.md; estimates are first-pass and unvalidated by any completed sprint.
